{
  "id": "ed47845c-a401-4842-ae3d-1466746e45d0",
  "prevId": "00000000-0000-0000-0000-000000000000",
  "version": "7",
  "dialect": "postgresql",
  "tables": {
    "public.book": {
      "name": "book",
      "schema": "",
      "columns": {
        "id": {
          "name": "id",
          "type": "uuid",
          "primaryKey": true,
          "notNull": true,
          "default": "gen_random_uuid()"
        },
        "title": {
          "name": "title",
          "type": "varchar(255)",
          "primaryKey": false,
          "notNull": true
        },
        "slug": {
          "name": "slug",
          "type": "varchar(255)",
          "primaryKey": false,
          "notNull": true
        },
        "jlpt_level": {
          "name": "jlpt_level",
          "type": "jlpt_level",
          "typeSchema": "public",
          "primaryKey": false,
          "notNull": true
        },
        "chapter_start": {
          "name": "chapter_start",
          "type": "integer",
          "primaryKey": false,
          "notNull": true
        },
        "chapter_end": {
          "name": "chapter_end",
          "type": "integer",
          "primaryKey": false,
          "notNull": true
        },
        "created_at": {
          "name": "created_at",
          "type": "text",
          "primaryKey": false,
          "notNull": true,
          "default": "'now()'"
        }
      },
      "indexes": {},
      "foreignKeys": {},
      "compositePrimaryKeys": {},
      "uniqueConstraints": {
        "book_slug_unique": {
          "name": "book_slug_unique",
          "nullsNotDistinct": false,
          "columns": [
            "slug"
          ]
        }
      },
      "policies": {},
      "checkConstraints": {},
      "isRLSEnabled": false
    },
    "public.chapter": {
      "name": "chapter",
      "schema": "",
      "columns": {
        "id": {
          "name": "id",
          "type": "uuid",
          "primaryKey": true,
          "notNull": true,
          "default": "gen_random_uuid()"
        },
        "book_id": {
          "name": "book_id",
          "type": "uuid",
          "primaryKey": false,
          "notNull": true
        },
        "chapter_number": {
          "name": "chapter_number",
          "type": "integer",
          "primaryKey": false,
          "notNull": true
        },
        "slug": {
          "name": "slug",
          "type": "varchar(255)",
          "primaryKey": false,
          "notNull": true
        },
        "vocab_count": {
          "name": "vocab_count",
          "type": "integer",
          "primaryKey": false,
          "notNull": true,
          "default": 0
        },
        "created_at": {
          "name": "created_at",
          "type": "text",
          "primaryKey": false,
          "notNull": true,
          "default": "'now()'"
        }
      },
      "indexes": {},
      "foreignKeys": {
        "chapter_book_id_book_id_fk": {
          "name": "chapter_book_id_book_id_fk",
          "tableFrom": "chapter",
          "tableTo": "book",
          "columnsFrom": [
            "book_id"
          ],
          "columnsTo": [
            "id"
          ],
          "onDelete": "cascade",
          "onUpdate": "no action"
        }
      },
      "compositePrimaryKeys": {},
      "uniqueConstraints": {
        "chapter_slug_unique": {
          "name": "chapter_slug_unique",
          "nullsNotDistinct": false,
          "columns": [
            "slug"
          ]
        }
      },
      "policies": {},
      "checkConstraints": {},
      "isRLSEnabled": false
    },
    "public.kana": {
      "name": "kana",
      "schema": "",
      "columns": {
        "id": {
          "name": "id",
          "type": "uuid",
          "primaryKey": true,
          "notNull": true,
          "default": "gen_random_uuid()"
        },
        "character": {
          "name": "character",
          "type": "varchar(10)",
          "primaryKey": false,
          "notNull": true
        },
        "romaji": {
          "name": "romaji",
          "type": "varchar(10)",
          "primaryKey": false,
          "notNull": true
        },
        "category": {
          "name": "category",
          "type": "kana_category",
          "typeSchema": "public",
          "primaryKey": false,
          "notNull": true
        },
        "row_group": {
          "name": "row_group",
          "type": "varchar(20)",
          "primaryKey": false,
          "notNull": true
        },
        "column_position": {
          "name": "column_position",
          "type": "smallint",
          "primaryKey": false,
          "notNull": true
        },
        "audio_url": {
          "name": "audio_url",
          "type": "text",
          "primaryKey": false,
          "notNull": false
        },
        "created_at": {
          "name": "created_at",
          "type": "text",
          "primaryKey": false,
          "notNull": true,
          "default": "'now()'"
        }
      },
      "indexes": {},
      "foreignKeys": {},
      "compositePrimaryKeys": {},
      "uniqueConstraints": {
        "kana_character_unique": {
          "name": "kana_character_unique",
          "nullsNotDistinct": false,
          "columns": [
            "character"
          ]
        }
      },
      "policies": {},
      "checkConstraints": {},
      "isRLSEnabled": false
    },
    "public.vocabulary": {
      "name": "vocabulary",
      "schema": "",
      "columns": {
        "id": {
          "name": "id",
          "type": "uuid",
          "primaryKey": true,
          "notNull": true,
          "default": "gen_random_uuid()"
        },
        "chapter_id": {
          "name": "chapter_id",
          "type": "uuid",
          "primaryKey": false,
          "notNull": true
        },
        "kanji": {
          "name": "kanji",
          "type": "varchar(100)",
          "primaryKey": false,
          "notNull": false
        },
        "hiragana": {
          "name": "hiragana",
          "type": "varchar(100)",
          "primaryKey": false,
          "notNull": true
        },
        "romaji": {
          "name": "romaji",
          "type": "varchar(100)",
          "primaryKey": false,
          "notNull": true
        },
        "meaning_id": {
          "name": "meaning_id",
          "type": "varchar(255)",
          "primaryKey": false,
          "notNull": true
        },
        "meaning_en": {
          "name": "meaning_en",
          "type": "varchar(255)",
          "primaryKey": false,
          "notNull": true
        },
        "word_type": {
          "name": "word_type",
          "type": "word_type",
          "typeSchema": "public",
          "primaryKey": false,
          "notNull": true
        },
        "jlpt_level": {
          "name": "jlpt_level",
          "type": "jlpt_level",
          "typeSchema": "public",
          "primaryKey": false,
          "notNull": true
        },
        "audio_url": {
          "name": "audio_url",
          "type": "text",
          "primaryKey": false,
          "notNull": false
        },
        "example_jp": {
          "name": "example_jp",
          "type": "text",
          "primaryKey": false,
          "notNull": false
        },
        "example_id": {
          "name": "example_id",
          "type": "text",
          "primaryKey": false,
          "notNull": false
        },
        "sort_order": {
          "name": "sort_order",
          "type": "smallint",
          "primaryKey": false,
          "notNull": true,
          "default": 0
        },
        "created_at": {
          "name": "created_at",
          "type": "text",
          "primaryKey": false,
          "notNull": true,
          "default": "'now()'"
        }
      },
      "indexes": {},
      "foreignKeys": {
        "vocabulary_chapter_id_chapter_id_fk": {
          "name": "vocabulary_chapter_id_chapter_id_fk",
          "tableFrom": "vocabulary",
          "tableTo": "chapter",
          "columnsFrom": [
            "chapter_id"
          ],
          "columnsTo": [
            "id"
          ],
          "onDelete": "cascade",
          "onUpdate": "no action"
        }
      },
      "compositePrimaryKeys": {},
      "uniqueConstraints": {},
      "policies": {},
      "checkConstraints": {},
      "isRLSEnabled": false
    },
    "public.user": {
      "name": "user",
      "schema": "",
      "columns": {
        "id": {
          "name": "id",
          "type": "uuid",
          "primaryKey": true,
          "notNull": true,
          "default": "gen_random_uuid()"
        },
        "supabase_auth_id": {
          "name": "supabase_auth_id",
          "type": "uuid",
          "primaryKey": false,
          "notNull": true
        },
        "email": {
          "name": "email",
          "type": "varchar(255)",
          "primaryKey": false,
          "notNull": true
        },
        "display_name": {
          "name": "display_name",
          "type": "varchar(100)",
          "primaryKey": false,
          "notNull": false
        },
        "avatar_url": {
          "name": "avatar_url",
          "type": "text",
          "primaryKey": false,
          "notNull": false
        },
        "jlpt_target": {
          "name": "jlpt_target",
          "type": "jlpt_level",
          "typeSchema": "public",
          "primaryKey": false,
          "notNull": false,
          "default": "'N5'"
        },
        "daily_goal_xp": {
          "name": "daily_goal_xp",
          "type": "daily_goal_xp",
          "typeSchema": "public",
          "primaryKey": false,
          "notNull": false,
          "default": "'30'"
        },
        "auto_play_audio": {
          "name": "auto_play_audio",
          "type": "boolean",
          "primaryKey": false,
          "notNull": true,
          "default": true
        },
        "show_romaji": {
          "name": "show_romaji",
          "type": "boolean",
          "primaryKey": false,
          "notNull": true,
          "default": true
        },
        "theme": {
          "name": "theme",
          "type": "theme",
          "typeSchema": "public",
          "primaryKey": false,
          "notNull": true,
          "default": "'system'"
        },
        "onboarding_done": {
          "name": "onboarding_done",
          "type": "boolean",
          "primaryKey": false,
          "notNull": true,
          "default": false
        },
        "hirakata_known": {
          "name": "hirakata_known",
          "type": "boolean",
          "primaryKey": false,
          "notNull": true,
          "default": false
        },
        "created_at": {
          "name": "created_at",
          "type": "text",
          "primaryKey": false,
          "notNull": true,
          "default": "'now()'"
        },
        "updated_at": {
          "name": "updated_at",
          "type": "text",
          "primaryKey": false,
          "notNull": true,
          "default": "'now()'"
        }
      },
      "indexes": {},
      "foreignKeys": {},
      "compositePrimaryKeys": {},
      "uniqueConstraints": {
        "user_supabase_auth_id_unique": {
          "name": "user_supabase_auth_id_unique",
          "nullsNotDistinct": false,
          "columns": [
            "supabase_auth_id"
          ]
        }
      },
      "policies": {},
      "checkConstraints": {},
      "isRLSEnabled": false
    },
    "public.review_log": {
      "name": "review_log",
      "schema": "",
      "columns": {
        "id": {
          "name": "id",
          "type": "uuid",
          "primaryKey": true,
          "notNull": true,
          "default": "gen_random_uuid()"
        },
        "user_id": {
          "name": "user_id",
          "type": "uuid",
          "primaryKey": false,
          "notNull": true
        },
        "card_id": {
          "name": "card_id",
          "type": "uuid",
          "primaryKey": false,
          "notNull": true
        },
        "rating": {
          "name": "rating",
          "type": "srs_rating",
          "typeSchema": "public",
          "primaryKey": false,
          "notNull": true
        },
        "prev_stability": {
          "name": "prev_stability",
          "type": "real",
          "primaryKey": false,
          "notNull": false
        },
        "new_stability": {
          "name": "new_stability",
          "type": "real",
          "primaryKey": false,
          "notNull": false
        },
        "prev_difficulty": {
          "name": "prev_difficulty",
          "type": "real",
          "primaryKey": false,
          "notNull": false
        },
        "new_difficulty": {
          "name": "new_difficulty",
          "type": "real",
          "primaryKey": false,
          "notNull": false
        },
        "prev_status": {
          "name": "prev_status",
          "type": "srs_status",
          "typeSchema": "public",
          "primaryKey": false,
          "notNull": false
        },
        "new_status": {
          "name": "new_status",
          "type": "srs_status",
          "typeSchema": "public",
          "primaryKey": false,
          "notNull": false
        },
        "review_duration_ms": {
          "name": "review_duration_ms",
          "type": "integer",
          "primaryKey": false,
          "notNull": false
        },
        "reviewed_at": {
          "name": "reviewed_at",
          "type": "text",
          "primaryKey": false,
          "notNull": true,
          "default": "'now()'"
        }
      },
      "indexes": {},
      "foreignKeys": {
        "review_log_user_id_user_id_fk": {
          "name": "review_log_user_id_user_id_fk",
          "tableFrom": "review_log",
          "tableTo": "user",
          "columnsFrom": [
            "user_id"
          ],
          "columnsTo": [
            "id"
          ],
          "onDelete": "cascade",
          "onUpdate": "no action"
        },
        "review_log_card_id_srs_card_id_fk": {
          "name": "review_log_card_id_srs_card_id_fk",
          "tableFrom": "review_log",
          "tableTo": "srs_card",
          "columnsFrom": [
            "card_id"
          ],
          "columnsTo": [
            "id"
          ],
          "onDelete": "cascade",
          "onUpdate": "no action"
        }
      },
      "compositePrimaryKeys": {},
      "uniqueConstraints": {},
      "policies": {},
      "checkConstraints": {},
      "isRLSEnabled": false
    },
    "public.srs_card": {
      "name": "srs_card",
      "schema": "",
      "columns": {
        "id": {
          "name": "id",
          "type": "uuid",
          "primaryKey": true,
          "notNull": true,
          "default": "gen_random_uuid()"
        },
        "user_id": {
          "name": "user_id",
          "type": "uuid",
          "primaryKey": false,
          "notNull": true
        },
        "vocabulary_id": {
          "name": "vocabulary_id",
          "type": "uuid",
          "primaryKey": false,
          "notNull": false
        },
        "kana_id": {
          "name": "kana_id",
          "type": "uuid",
          "primaryKey": false,
          "notNull": false
        },
        "status": {
          "name": "status",
          "type": "srs_status",
          "typeSchema": "public",
          "primaryKey": false,
          "notNull": true,
          "default": "'new'"
        },
        "stability": {
          "name": "stability",
          "type": "real",
          "primaryKey": false,
          "notNull": true,
          "default": 0
        },
        "difficulty": {
          "name": "difficulty",
          "type": "real",
          "primaryKey": false,
          "notNull": true,
          "default": 0
        },
        "due_date": {
          "name": "due_date",
          "type": "text",
          "primaryKey": false,
          "notNull": true,
          "default": "'now()'"
        },
        "scheduled_days": {
          "name": "scheduled_days",
          "type": "integer",
          "primaryKey": false,
          "notNull": true,
          "default": 0
        },
        "reps": {
          "name": "reps",
          "type": "integer",
          "primaryKey": false,
          "notNull": true,
          "default": 0
        },
        "lapses": {
          "name": "lapses",
          "type": "integer",
          "primaryKey": false,
          "notNull": true,
          "default": 0
        },
        "created_at": {
          "name": "created_at",
          "type": "text",
          "primaryKey": false,
          "notNull": true,
          "default": "'now()'"
        },
        "updated_at": {
          "name": "updated_at",
          "type": "text",
          "primaryKey": false,
          "notNull": true,
          "default": "'now()'"
        }
      },
      "indexes": {},
      "foreignKeys": {
        "srs_card_user_id_user_id_fk": {
          "name": "srs_card_user_id_user_id_fk",
          "tableFrom": "srs_card",
          "tableTo": "user",
          "columnsFrom": [
            "user_id"
          ],
          "columnsTo": [
            "id"
          ],
          "onDelete": "cascade",
          "onUpdate": "no action"
        },
        "srs_card_vocabulary_id_vocabulary_id_fk": {
          "name": "srs_card_vocabulary_id_vocabulary_id_fk",
          "tableFrom": "srs_card",
          "tableTo": "vocabulary",
          "columnsFrom": [
            "vocabulary_id"
          ],
          "columnsTo": [
            "id"
          ],
          "onDelete": "cascade",
          "onUpdate": "no action"
        },
        "srs_card_kana_id_kana_id_fk": {
          "name": "srs_card_kana_id_kana_id_fk",
          "tableFrom": "srs_card",
          "tableTo": "kana",
          "columnsFrom": [
            "kana_id"
          ],
          "columnsTo": [
            "id"
          ],
          "onDelete": "cascade",
          "onUpdate": "no action"
        }
      },
      "compositePrimaryKeys": {},
      "uniqueConstraints": {},
      "policies": {},
      "checkConstraints": {
        "vocab_xor_kana": {
          "name": "vocab_xor_kana",
          "value": "(\"srs_card\".\"vocabulary_id\" IS NOT NULL AND \"srs_card\".\"kana_id\" IS NULL) OR (\"srs_card\".\"vocabulary_id\" IS NULL AND \"srs_card\".\"kana_id\" IS NOT NULL)"
        }
      },
      "isRLSEnabled": false
    },
    "public.quiz_answer": {
      "name": "quiz_answer",
      "schema": "",
      "columns": {
        "id": {
          "name": "id",
          "type": "uuid",
          "primaryKey": true,
          "notNull": true,
          "default": "gen_random_uuid()"
        },
        "session_id": {
          "name": "session_id",
          "type": "uuid",
          "primaryKey": false,
          "notNull": true
        },
        "question_number": {
          "name": "question_number",
          "type": "smallint",
          "primaryKey": false,
          "notNull": true
        },
        "question_type": {
          "name": "question_type",
          "type": "question_type",
          "typeSchema": "public",
          "primaryKey": false,
          "notNull": true
        },
        "vocabulary_id": {
          "name": "vocabulary_id",
          "type": "uuid",
          "primaryKey": false,
          "notNull": false
        },
        "kana_id": {
          "name": "kana_id",
          "type": "uuid",
          "primaryKey": false,
          "notNull": false
        },
        "question_text": {
          "name": "question_text",
          "type": "text",
          "primaryKey": false,
          "notNull": true
        },
        "correct_answer": {
          "name": "correct_answer",
          "type": "varchar(255)",
          "primaryKey": false,
          "notNull": true
        },
        "options": {
          "name": "options",
          "type": "jsonb",
          "primaryKey": false,
          "notNull": false
        },
        "user_answer": {
          "name": "user_answer",
          "type": "varchar(255)",
          "primaryKey": false,
          "notNull": false
        },
        "is_correct": {
          "name": "is_correct",
          "type": "boolean",
          "primaryKey": false,
          "notNull": false
        },
        "answered_at": {
          "name": "answered_at",
          "type": "text",
          "primaryKey": false,
          "notNull": false
        }
      },
      "indexes": {},
      "foreignKeys": {
        "quiz_answer_session_id_quiz_session_id_fk": {
          "name": "quiz_answer_session_id_quiz_session_id_fk",
          "tableFrom": "quiz_answer",
          "tableTo": "quiz_session",
          "columnsFrom": [
            "session_id"
          ],
          "columnsTo": [
            "id"
          ],
          "onDelete": "cascade",
          "onUpdate": "no action"
        },
        "quiz_answer_vocabulary_id_vocabulary_id_fk": {
          "name": "quiz_answer_vocabulary_id_vocabulary_id_fk",
          "tableFrom": "quiz_answer",
          "tableTo": "vocabulary",
          "columnsFrom": [
            "vocabulary_id"
          ],
          "columnsTo": [
            "id"
          ],
          "onDelete": "set null",
          "onUpdate": "no action"
        },
        "quiz_answer_kana_id_kana_id_fk": {
          "name": "quiz_answer_kana_id_kana_id_fk",
          "tableFrom": "quiz_answer",
          "tableTo": "kana",
          "columnsFrom": [
            "kana_id"
          ],
          "columnsTo": [
            "id"
          ],
          "onDelete": "set null",
          "onUpdate": "no action"
        }
      },
      "compositePrimaryKeys": {},
      "uniqueConstraints": {},
      "policies": {},
      "checkConstraints": {},
      "isRLSEnabled": false
    },
    "public.quiz_session": {
      "name": "quiz_session",
      "schema": "",
      "columns": {
        "id": {
          "name": "id",
          "type": "uuid",
          "primaryKey": true,
          "notNull": true,
          "default": "gen_random_uuid()"
        },
        "user_id": {
          "name": "user_id",
          "type": "uuid",
          "primaryKey": false,
          "notNull": true
        },
        "chapter_id": {
          "name": "chapter_id",
          "type": "uuid",
          "primaryKey": false,
          "notNull": false
        },
        "kana_category": {
          "name": "kana_category",
          "type": "kana_category",
          "typeSchema": "public",
          "primaryKey": false,
          "notNull": false
        },
        "total_questions": {
          "name": "total_questions",
          "type": "integer",
          "primaryKey": false,
          "notNull": true
        },
        "correct_count": {
          "name": "correct_count",
          "type": "integer",
          "primaryKey": false,
          "notNull": true,
          "default": 0
        },
        "score_percent": {
          "name": "score_percent",
          "type": "real",
          "primaryKey": false,
          "notNull": false
        },
        "xp_earned": {
          "name": "xp_earned",
          "type": "integer",
          "primaryKey": false,
          "notNull": true,
          "default": 0
        },
        "time_spent_ms": {
          "name": "time_spent_ms",
          "type": "integer",
          "primaryKey": false,
          "notNull": false
        },
        "is_completed": {
          "name": "is_completed",
          "type": "boolean",
          "primaryKey": false,
          "notNull": true,
          "default": false
        },
        "is_perfect": {
          "name": "is_perfect",
          "type": "boolean",
          "primaryKey": false,
          "notNull": true,
          "default": false
        },
        "created_at": {
          "name": "created_at",
          "type": "text",
          "primaryKey": false,
          "notNull": true,
          "default": "'now()'"
        },
        "completed_at": {
          "name": "completed_at",
          "type": "text",
          "primaryKey": false,
          "notNull": false
        }
      },
      "indexes": {},
      "foreignKeys": {
        "quiz_session_user_id_user_id_fk": {
          "name": "quiz_session_user_id_user_id_fk",
          "tableFrom": "quiz_session",
          "tableTo": "user",
          "columnsFrom": [
            "user_id"
          ],
          "columnsTo": [
            "id"
          ],
          "onDelete": "cascade",
          "onUpdate": "no action"
        },
        "quiz_session_chapter_id_chapter_id_fk": {
          "name": "quiz_session_chapter_id_chapter_id_fk",
          "tableFrom": "quiz_session",
          "tableTo": "chapter",
          "columnsFrom": [
            "chapter_id"
          ],
          "columnsTo": [
            "id"
          ],
          "onDelete": "set null",
          "onUpdate": "no action"
        }
      },
      "compositePrimaryKeys": {},
      "uniqueConstraints": {},
      "policies": {},
      "checkConstraints": {},
      "isRLSEnabled": false
    },
    "public.achievement": {
      "name": "achievement",
      "schema": "",
      "columns": {
        "id": {
          "name": "id",
          "type": "uuid",
          "primaryKey": true,
          "notNull": true,
          "default": "gen_random_uuid()"
        },
        "name": {
          "name": "name",
          "type": "varchar(255)",
          "primaryKey": false,
          "notNull": true
        },
        "description": {
          "name": "description",
          "type": "text",
          "primaryKey": false,
          "notNull": true
        },
        "icon": {
          "name": "icon",
          "type": "varchar(100)",
          "primaryKey": false,
          "notNull": true
        },
        "type": {
          "name": "type",
          "type": "achievement_type",
          "typeSchema": "public",
          "primaryKey": false,
          "notNull": true
        },
        "condition": {
          "name": "condition",
          "type": "jsonb",
          "primaryKey": false,
          "notNull": true
        },
        "xp_reward": {
          "name": "xp_reward",
          "type": "integer",
          "primaryKey": false,
          "notNull": true,
          "default": 0
        },
        "created_at": {
          "name": "created_at",
          "type": "text",
          "primaryKey": false,
          "notNull": true,
          "default": "'now()'"
        }
      },
      "indexes": {},
      "foreignKeys": {},
      "compositePrimaryKeys": {},
      "uniqueConstraints": {},
      "policies": {},
      "checkConstraints": {},
      "isRLSEnabled": false
    },
    "public.achievement_unlock": {
      "name": "achievement_unlock",
      "schema": "",
      "columns": {
        "id": {
          "name": "id",
          "type": "uuid",
          "primaryKey": true,
          "notNull": true,
          "default": "gen_random_uuid()"
        },
        "user_id": {
          "name": "user_id",
          "type": "uuid",
          "primaryKey": false,
          "notNull": true
        },
        "achievement_id": {
          "name": "achievement_id",
          "type": "uuid",
          "primaryKey": false,
          "notNull": true
        },
        "unlocked_at": {
          "name": "unlocked_at",
          "type": "text",
          "primaryKey": false,
          "notNull": true,
          "default": "'now()'"
        }
      },
      "indexes": {},
      "foreignKeys": {
        "achievement_unlock_user_id_user_id_fk": {
          "name": "achievement_unlock_user_id_user_id_fk",
          "tableFrom": "achievement_unlock",
          "tableTo": "user",
          "columnsFrom": [
            "user_id"
          ],
          "columnsTo": [
            "id"
          ],
          "onDelete": "cascade",
          "onUpdate": "no action"
        },
        "achievement_unlock_achievement_id_achievement_id_fk": {
          "name": "achievement_unlock_achievement_id_achievement_id_fk",
          "tableFrom": "achievement_unlock",
          "tableTo": "achievement",
          "columnsFrom": [
            "achievement_id"
          ],
          "columnsTo": [
            "id"
          ],
          "onDelete": "cascade",
          "onUpdate": "no action"
        }
      },
      "compositePrimaryKeys": {},
      "uniqueConstraints": {},
      "policies": {},
      "checkConstraints": {},
      "isRLSEnabled": false
    },
    "public.daily_activity": {
      "name": "daily_activity",
      "schema": "",
      "columns": {
        "id": {
          "name": "id",
          "type": "uuid",
          "primaryKey": true,
          "notNull": true,
          "default": "gen_random_uuid()"
        },
        "user_id": {
          "name": "user_id",
          "type": "uuid",
          "primaryKey": false,
          "notNull": true
        },
        "activity_date": {
          "name": "activity_date",
          "type": "date",
          "primaryKey": false,
          "notNull": true
        },
        "reviews_count": {
          "name": "reviews_count",
          "type": "integer",
          "primaryKey": false,
          "notNull": true,
          "default": 0
        },
        "quiz_count": {
          "name": "quiz_count",
          "type": "integer",
          "primaryKey": false,
          "notNull": true,
          "default": 0
        },
        "xp_earned": {
          "name": "xp_earned",
          "type": "integer",
          "primaryKey": false,
          "notNull": true,
          "default": 0
        },
        "goal_met": {
          "name": "goal_met",
          "type": "boolean",
          "primaryKey": false,
          "notNull": true,
          "default": false
        },
        "created_at": {
          "name": "created_at",
          "type": "text",
          "primaryKey": false,
          "notNull": true,
          "default": "'now()'"
        }
      },
      "indexes": {},
      "foreignKeys": {
        "daily_activity_user_id_user_id_fk": {
          "name": "daily_activity_user_id_user_id_fk",
          "tableFrom": "daily_activity",
          "tableTo": "user",
          "columnsFrom": [
            "user_id"
          ],
          "columnsTo": [
            "id"
          ],
          "onDelete": "cascade",
          "onUpdate": "no action"
        }
      },
      "compositePrimaryKeys": {},
      "uniqueConstraints": {},
      "policies": {},
      "checkConstraints": {},
      "isRLSEnabled": false
    },
    "public.user_chapter_progress": {
      "name": "user_chapter_progress",
      "schema": "",
      "columns": {
        "id": {
          "name": "id",
          "type": "uuid",
          "primaryKey": true,
          "notNull": true,
          "default": "gen_random_uuid()"
        },
        "user_id": {
          "name": "user_id",
          "type": "uuid",
          "primaryKey": false,
          "notNull": true
        },
        "chapter_id": {
          "name": "chapter_id",
          "type": "uuid",
          "primaryKey": false,
          "notNull": true
        },
        "vocab_seen": {
          "name": "vocab_seen",
          "type": "integer",
          "primaryKey": false,
          "notNull": true,
          "default": 0
        },
        "vocab_learning": {
          "name": "vocab_learning",
          "type": "integer",
          "primaryKey": false,
          "notNull": true,
          "default": 0
        },
        "vocab_review": {
          "name": "vocab_review",
          "type": "integer",
          "primaryKey": false,
          "notNull": true,
          "default": 0
        },
        "completion_percent": {
          "name": "completion_percent",
          "type": "integer",
          "primaryKey": false,
          "notNull": true,
          "default": 0
        },
        "best_quiz_score": {
          "name": "best_quiz_score",
          "type": "integer",
          "primaryKey": false,
          "notNull": false
        },
        "created_at": {
          "name": "created_at",
          "type": "text",
          "primaryKey": false,
          "notNull": true,
          "default": "'now()'"
        },
        "updated_at": {
          "name": "updated_at",
          "type": "text",
          "primaryKey": false,
          "notNull": true,
          "default": "'now()'"
        }
      },
      "indexes": {},
      "foreignKeys": {
        "user_chapter_progress_user_id_user_id_fk": {
          "name": "user_chapter_progress_user_id_user_id_fk",
          "tableFrom": "user_chapter_progress",
          "tableTo": "user",
          "columnsFrom": [
            "user_id"
          ],
          "columnsTo": [
            "id"
          ],
          "onDelete": "cascade",
          "onUpdate": "no action"
        },
        "user_chapter_progress_chapter_id_chapter_id_fk": {
          "name": "user_chapter_progress_chapter_id_chapter_id_fk",
          "tableFrom": "user_chapter_progress",
          "tableTo": "chapter",
          "columnsFrom": [
            "chapter_id"
          ],
          "columnsTo": [
            "id"
          ],
          "onDelete": "cascade",
          "onUpdate": "no action"
        }
      },
      "compositePrimaryKeys": {},
      "uniqueConstraints": {},
      "policies": {},
      "checkConstraints": {},
      "isRLSEnabled": false
    },
    "public.user_gamification": {
      "name": "user_gamification",
      "schema": "",
      "columns": {
        "id": {
          "name": "id",
          "type": "uuid",
          "primaryKey": true,
          "notNull": true,
          "default": "gen_random_uuid()"
        },
        "user_id": {
          "name": "user_id",
          "type": "uuid",
          "primaryKey": false,
          "notNull": true
        },
        "total_xp": {
          "name": "total_xp",
          "type": "integer",
          "primaryKey": false,
          "notNull": true,
          "default": 0
        },
        "current_level": {
          "name": "current_level",
          "type": "integer",
          "primaryKey": false,
          "notNull": true,
          "default": 1
        },
        "current_streak": {
          "name": "current_streak",
          "type": "integer",
          "primaryKey": false,
          "notNull": true,
          "default": 0
        },
        "longest_streak": {
          "name": "longest_streak",
          "type": "integer",
          "primaryKey": false,
          "notNull": true,
          "default": 0
        },
        "streak_freezes": {
          "name": "streak_freezes",
          "type": "integer",
          "primaryKey": false,
          "notNull": true,
          "default": 0
        },
        "last_activity_date": {
          "name": "last_activity_date",
          "type": "date",
          "primaryKey": false,
          "notNull": false
        },
        "total_reviews": {
          "name": "total_reviews",
          "type": "integer",
          "primaryKey": false,
          "notNull": true,
          "default": 0
        },
        "total_words_learned": {
          "name": "total_words_learned",
          "type": "integer",
          "primaryKey": false,
          "notNull": true,
          "default": 0
        },
        "daily_xp_earned": {
          "name": "daily_xp_earned",
          "type": "integer",
          "primaryKey": false,
          "notNull": true,
          "default": 0
        },
        "daily_goal_met": {
          "name": "daily_goal_met",
          "type": "boolean",
          "primaryKey": false,
          "notNull": true,
          "default": false
        },
        "created_at": {
          "name": "created_at",
          "type": "text",
          "primaryKey": false,
          "notNull": true,
          "default": "'now()'"
        },
        "updated_at": {
          "name": "updated_at",
          "type": "text",
          "primaryKey": false,
          "notNull": true,
          "default": "'now()'"
        }
      },
      "indexes": {},
      "foreignKeys": {
        "user_gamification_user_id_user_id_fk": {
          "name": "user_gamification_user_id_user_id_fk",
          "tableFrom": "user_gamification",
          "tableTo": "user",
          "columnsFrom": [
            "user_id"
          ],
          "columnsTo": [
            "id"
          ],
          "onDelete": "cascade",
          "onUpdate": "no action"
        }
      },
      "compositePrimaryKeys": {},
      "uniqueConstraints": {
        "user_gamification_user_id_unique": {
          "name": "user_gamification_user_id_unique",
          "nullsNotDistinct": false,
          "columns": [
            "user_id"
          ]
        }
      },
      "policies": {},
      "checkConstraints": {},
      "isRLSEnabled": false
    },
    "public.xp_transaction": {
      "name": "xp_transaction",
      "schema": "",
      "columns": {
        "id": {
          "name": "id",
          "type": "uuid",
          "primaryKey": true,
          "notNull": true,
          "default": "gen_random_uuid()"
        },
        "user_id": {
          "name": "user_id",
          "type": "uuid",
          "primaryKey": false,
          "notNull": true
        },
        "source": {
          "name": "source",
          "type": "xp_source",
          "typeSchema": "public",
          "primaryKey": false,
          "notNull": true
        },
        "amount": {
          "name": "amount",
          "type": "integer",
          "primaryKey": false,
          "notNull": true
        },
        "description": {
          "name": "description",
          "type": "text",
          "primaryKey": false,
          "notNull": false
        },
        "reference_id": {
          "name": "reference_id",
          "type": "uuid",
          "primaryKey": false,
          "notNull": false
        },
        "created_at": {
          "name": "created_at",
          "type": "text",
          "primaryKey": false,
          "notNull": true,
          "default": "'now()'"
        }
      },
      "indexes": {},
      "foreignKeys": {
        "xp_transaction_user_id_user_id_fk": {
          "name": "xp_transaction_user_id_user_id_fk",
          "tableFrom": "xp_transaction",
          "tableTo": "user",
          "columnsFrom": [
            "user_id"
          ],
          "columnsTo": [
            "id"
          ],
          "onDelete": "cascade",
          "onUpdate": "no action"
        }
      },
      "compositePrimaryKeys": {},
      "uniqueConstraints": {},
      "policies": {},
      "checkConstraints": {},
      "isRLSEnabled": false
    },
    "public.ai_chat_message": {
      "name": "ai_chat_message",
      "schema": "",
      "columns": {
        "id": {
          "name": "id",
          "type": "uuid",
          "primaryKey": true,
          "notNull": true,
          "default": "gen_random_uuid()"
        },
        "session_id": {
          "name": "session_id",
          "type": "uuid",
          "primaryKey": false,
          "notNull": true
        },
        "role": {
          "name": "role",
          "type": "chat_role",
          "typeSchema": "public",
          "primaryKey": false,
          "notNull": true
        },
        "content": {
          "name": "content",
          "type": "text",
          "primaryKey": false,
          "notNull": true
        },
        "provider_used": {
          "name": "provider_used",
          "type": "varchar(50)",
          "primaryKey": false,
          "notNull": false
        },
        "created_at": {
          "name": "created_at",
          "type": "text",
          "primaryKey": false,
          "notNull": true,
          "default": "'now()'"
        }
      },
      "indexes": {},
      "foreignKeys": {
        "ai_chat_message_session_id_ai_chat_session_id_fk": {
          "name": "ai_chat_message_session_id_ai_chat_session_id_fk",
          "tableFrom": "ai_chat_message",
          "tableTo": "ai_chat_session",
          "columnsFrom": [
            "session_id"
          ],
          "columnsTo": [
            "id"
          ],
          "onDelete": "cascade",
          "onUpdate": "no action"
        }
      },
      "compositePrimaryKeys": {},
      "uniqueConstraints": {},
      "policies": {},
      "checkConstraints": {},
      "isRLSEnabled": false
    },
    "public.ai_chat_session": {
      "name": "ai_chat_session",
      "schema": "",
      "columns": {
        "id": {
          "name": "id",
          "type": "uuid",
          "primaryKey": true,
          "notNull": true,
          "default": "gen_random_uuid()"
        },
        "user_id": {
          "name": "user_id",
          "type": "uuid",
          "primaryKey": false,
          "notNull": true
        },
        "title": {
          "name": "title",
          "type": "varchar(255)",
          "primaryKey": false,
          "notNull": false
        },
        "message_count": {
          "name": "message_count",
          "type": "integer",
          "primaryKey": false,
          "notNull": true,
          "default": 0
        },
        "created_at": {
          "name": "created_at",
          "type": "text",
          "primaryKey": false,
          "notNull": true,
          "default": "'now()'"
        },
        "updated_at": {
          "name": "updated_at",
          "type": "text",
          "primaryKey": false,
          "notNull": true,
          "default": "'now()'"
        }
      },
      "indexes": {},
      "foreignKeys": {
        "ai_chat_session_user_id_user_id_fk": {
          "name": "ai_chat_session_user_id_user_id_fk",
          "tableFrom": "ai_chat_session",
          "tableTo": "user",
          "columnsFrom": [
            "user_id"
          ],
          "columnsTo": [
            "id"
          ],
          "onDelete": "cascade",
          "onUpdate": "no action"
        }
      },
      "compositePrimaryKeys": {},
      "uniqueConstraints": {},
      "policies": {},
      "checkConstraints": {},
      "isRLSEnabled": false
    },
    "public.ai_question_template": {
      "name": "ai_question_template",
      "schema": "",
      "columns": {
        "id": {
          "name": "id",
          "type": "uuid",
          "primaryKey": true,
          "notNull": true,
          "default": "gen_random_uuid()"
        },
        "vocabulary_id": {
          "name": "vocabulary_id",
          "type": "uuid",
          "primaryKey": false,
          "notNull": true
        },
        "question_type": {
          "name": "question_type",
          "type": "question_type",
          "typeSchema": "public",
          "primaryKey": false,
          "notNull": true
        },
        "question_text": {
          "name": "question_text",
          "type": "text",
          "primaryKey": false,
          "notNull": true
        },
        "correct_answer": {
          "name": "correct_answer",
          "type": "varchar(255)",
          "primaryKey": false,
          "notNull": true
        },
        "wrong_answers": {
          "name": "wrong_answers",
          "type": "jsonb",
          "primaryKey": false,
          "notNull": true
        },
        "created_at": {
          "name": "created_at",
          "type": "text",
          "primaryKey": false,
          "notNull": true,
          "default": "'now()'"
        }
      },
      "indexes": {},
      "foreignKeys": {
        "ai_question_template_vocabulary_id_vocabulary_id_fk": {
          "name": "ai_question_template_vocabulary_id_vocabulary_id_fk",
          "tableFrom": "ai_question_template",
          "tableTo": "vocabulary",
          "columnsFrom": [
            "vocabulary_id"
          ],
          "columnsTo": [
            "id"
          ],
          "onDelete": "cascade",
          "onUpdate": "no action"
        }
      },
      "compositePrimaryKeys": {},
      "uniqueConstraints": {},
      "policies": {},
      "checkConstraints": {},
      "isRLSEnabled": false
    },
    "public.ai_response_cache": {
      "name": "ai_response_cache",
      "schema": "",
      "columns": {
        "id": {
          "name": "id",
          "type": "uuid",
          "primaryKey": true,
          "notNull": true,
          "default": "gen_random_uuid()"
        },
        "prompt_hash": {
          "name": "prompt_hash",
          "type": "varchar(64)",
          "primaryKey": false,
          "notNull": true
        },
        "response_text": {
          "name": "response_text",
          "type": "text",
          "primaryKey": false,
          "notNull": true
        },
        "provider": {
          "name": "provider",
          "type": "varchar(50)",
          "primaryKey": false,
          "notNull": true
        },
        "hit_count": {
          "name": "hit_count",
          "type": "integer",
          "primaryKey": false,
          "notNull": true,
          "default": 1
        },
        "created_at": {
          "name": "created_at",
          "type": "text",
          "primaryKey": false,
          "notNull": true,
          "default": "'now()'"
        }
      },
      "indexes": {},
      "foreignKeys": {},
      "compositePrimaryKeys": {},
      "uniqueConstraints": {
        "ai_response_cache_prompt_hash_unique": {
          "name": "ai_response_cache_prompt_hash_unique",
          "nullsNotDistinct": false,
          "columns": [
            "prompt_hash"
          ]
        }
      },
      "policies": {},
      "checkConstraints": {},
      "isRLSEnabled": false
    },
    "public.pronunciation_attempt": {
      "name": "pronunciation_attempt",
      "schema": "",
      "columns": {
        "id": {
          "name": "id",
          "type": "uuid",
          "primaryKey": true,
          "notNull": true,
          "default": "gen_random_uuid()"
        },
        "user_id": {
          "name": "user_id",
          "type": "uuid",
          "primaryKey": false,
          "notNull": true
        },
        "vocabulary_id": {
          "name": "vocabulary_id",
          "type": "uuid",
          "primaryKey": false,
          "notNull": false
        },
        "kana_id": {
          "name": "kana_id",
          "type": "uuid",
          "primaryKey": false,
          "notNull": false
        },
        "expected_text": {
          "name": "expected_text",
          "type": "varchar(255)",
          "primaryKey": false,
          "notNull": true
        },
        "recognized_text": {
          "name": "recognized_text",
          "type": "varchar(255)",
          "primaryKey": false,
          "notNull": false
        },
        "accuracy_score": {
          "name": "accuracy_score",
          "type": "real",
          "primaryKey": false,
          "notNull": false
        },
        "created_at": {
          "name": "created_at",
          "type": "text",
          "primaryKey": false,
          "notNull": true,
          "default": "'now()'"
        }
      },
      "indexes": {},
      "foreignKeys": {
        "pronunciation_attempt_user_id_user_id_fk": {
          "name": "pronunciation_attempt_user_id_user_id_fk",
          "tableFrom": "pronunciation_attempt",
          "tableTo": "user",
          "columnsFrom": [
            "user_id"
          ],
          "columnsTo": [
            "id"
          ],
          "onDelete": "cascade",
          "onUpdate": "no action"
        },
        "pronunciation_attempt_vocabulary_id_vocabulary_id_fk": {
          "name": "pronunciation_attempt_vocabulary_id_vocabulary_id_fk",
          "tableFrom": "pronunciation_attempt",
          "tableTo": "vocabulary",
          "columnsFrom": [
            "vocabulary_id"
          ],
          "columnsTo": [
            "id"
          ],
          "onDelete": "set null",
          "onUpdate": "no action"
        },
        "pronunciation_attempt_kana_id_kana_id_fk": {
          "name": "pronunciation_attempt_kana_id_kana_id_fk",
          "tableFrom": "pronunciation_attempt",
          "tableTo": "kana",
          "columnsFrom": [
            "kana_id"
          ],
          "columnsTo": [
            "id"
          ],
          "onDelete": "set null",
          "onUpdate": "no action"
        }
      },
      "compositePrimaryKeys": {},
      "uniqueConstraints": {},
      "policies": {},
      "checkConstraints": {},
      "isRLSEnabled": false
    }
  },
  "enums": {
    "public.achievement_type": {
      "name": "achievement_type",
      "schema": "public",
      "values": [
        "streak",
        "review_count",
        "quiz_score",
        "words_learned",
        "level",
        "special"
      ]
    },
    "public.chat_role": {
      "name": "chat_role",
      "schema": "public",
      "values": [
        "user",
        "assistant",
        "system"
      ]
    },
    "public.daily_goal_xp": {
      "name": "daily_goal_xp",
      "schema": "public",
      "values": [
        "30",
        "50",
        "100",
        "200"
      ]
    },
    "public.jlpt_level": {
      "name": "jlpt_level",
      "schema": "public",
      "values": [
        "N5",
        "N4",
        "N3",
        "N2",
        "N1"
      ]
    },
    "public.kana_category": {
      "name": "kana_category",
      "schema": "public",
      "values": [
        "hiragana_basic",
        "hiragana_dakuten",
        "hiragana_combo",
        "katakana_basic",
        "katakana_dakuten",
        "katakana_combo"
      ]
    },
    "public.question_type": {
      "name": "question_type",
      "schema": "public",
      "values": [
        "meaning_to_word",
        "word_to_meaning",
        "audio_to_word",
        "audio_to_meaning",
        "kanji_to_hiragana",
        "hiragana_to_kanji",
        "fill_in_blank"
      ]
    },
    "public.srs_rating": {
      "name": "srs_rating",
      "schema": "public",
      "values": [
        "again",
        "hard",
        "good",
        "easy"
      ]
    },
    "public.srs_status": {
      "name": "srs_status",
      "schema": "public",
      "values": [
        "new",
        "learning",
        "review",
        "relearning"
      ]
    },
    "public.theme": {
      "name": "theme",
      "schema": "public",
      "values": [
        "light",
        "dark",
        "system"
      ]
    },
    "public.word_type": {
      "name": "word_type",
      "schema": "public",
      "values": [
        "noun",
        "verb",
        "i_adjective",
        "na_adjective",
        "adverb",
        "particle",
        "conjunction",
        "expression",
        "counter",
        "prefix",
        "suffix",
        "pronoun",
        "interjection"
      ]
    },
    "public.xp_source": {
      "name": "xp_source",
      "schema": "public",
      "values": [
        "review",
        "quiz",
        "perfect_quiz",
        "streak_bonus",
        "achievement",
        "daily_bonus"
      ]
    }
  },
  "schemas": {},
  "sequences": {},
  "roles": {},
  "policies": {},
  "views": {},
  "_meta": {
    "columns": {},
    "schemas": {},
    "tables": {}
  }
}